{
  "name": "News",
  "fields": [
    {
      "fieldName": "title",
      "fieldType": "String"
    },
    {
      "fieldName": "content",
      "fieldType": "byte[]",
      "fieldTypeBlobContent": "text"
    },
    {
      "fieldName": "top",
      "fieldType": "Boolean"
    },
    {
      "fieldName": "topTime",
      "fieldType": "Instant"
    },
    {
      "fieldName": "createTime",
      "fieldType": "Instant"
    },
    {
      "fieldName": "updateTime",
      "fieldType": "Instant"
    },
    {
      "fieldName": "readCount",
      "fieldType": "Long"
    }
  ],
  "relationships": [
    {
      "relationshipType": "one-to-many",
      "otherEntityName": "comments",
      "otherEntityRelationshipName": "news",
      "relationshipName": "comments"
    }
  ],
  "entityTableName": "news",
  "dto": "no",
  "pagination": "no",
  "service": "no",
  "jpaMetamodelFiltering": false,
  "fluentMethods": true,
  "readOnly": false,
  "embedded": false,
  "applications": "*",
  "changelogDate": "20211130071758"
}
